{
  "schematics": {
    "ng-add": {
      "description": "Setup the package @rxap/config for the workspace.",
      "factory": "./src/schematics/ng-add/index",
      "schema": "./src/schematics/ng-add/schema.json"
    },
    "side-load": {
      "description": "Add a side load config to the project main file.",
      "factory": "./src/schematics/side-load/index",
      "schema": "./src/schematics/side-load/schema.json"
    }
  },
  "$schema": "../../node_modules/@angular-devkit/schematics/collection-schema.json"
}